sphinxcontrib/budoux.py
sphinxcontrib_budoux-0.1.6.dist-info/LICENSE
sphinxcontrib_budoux-0.1.6.dist-info/METADATA
sphinxcontrib_budoux-0.1.6.dist-info/WHEEL
sphinxcontrib_budoux-0.1.6.dist-info/RECORD
